molscene/Scene.py
molscene/__init__.py
molscene/_version.py
molscene/py.typed
molscene/tests/__init__.py
molscene/tests/test_Scene.py
molscene/tests/test_operators.py
molscene/utils/ChainNameGenerator.py
molscene/utils/PdbxContainers.py
molscene/utils/PdbxReader.py
molscene/utils/PdbxWriter.py
molscene/utils/__init__.py
molscene/utils/parsers.py
molscene-0.1.2.dist-info/licenses/LICENSE
molscene-0.1.2.dist-info/METADATA
molscene-0.1.2.dist-info/WHEEL
molscene-0.1.2.dist-info/top_level.txt
molscene-0.1.2.dist-info/RECORD
