Metadata-Version: 2.4
Name: molscene
Version: 0.1.2
Summary: PDB/mmCIF file parsing using pandas DataFrames
Author-email: Carlos Bueno <carlos.bueno@rice.edu>
License-Expression: MIT
Classifier: Programming Language :: Python :: 3
Requires-Python: >=3.8
License-File: LICENSE
Requires-Dist: pandas>=1.3.3
Requires-Dist: numpy>=1.21.0
Provides-Extra: test
Requires-Dist: pytest>=6.1.2; extra == "test"
Dynamic: license-file
